TCPClient/TCPClient.py
TCPClient/__init__.py
libs/__init__.py
libs/clientAbstract.py
libs/clientQt.py
libs/clientSocket.py
libs/frontend.py
TCPClient-0.0.25.dist-info/LICENSE
TCPClient-0.0.25.dist-info/METADATA
TCPClient-0.0.25.dist-info/WHEEL
TCPClient-0.0.25.dist-info/entry_points.txt
TCPClient-0.0.25.dist-info/top_level.txt
TCPClient-0.0.25.dist-info/RECORD
